invisible_backdoor_detector/__init_.py
invisible_backdoor_detector/helper.py
invisible_backdoor_detector/main.py
invisible_backdoor_detector-0.1.0.dist-info/entry_points.txt
invisible_backdoor_detector-0.1.0.dist-info/LICENSE
invisible_backdoor_detector-0.1.0.dist-info/WHEEL
invisible_backdoor_detector-0.1.0.dist-info/METADATA
invisible_backdoor_detector-0.1.0.dist-info/RECORD
