Metadata-Version: 2.1
Name: invisible-backdoor-detector
Version: 0.1.0
Summary: A simple tool to spot and remove Bidi characters that could lead to an invisible backdoor
License: MIT
Author: SecSI
Author-email: dev@secsi.io
Requires-Python: >=3.8,<4.0
Classifier: License :: OSI Approved :: MIT License
Classifier: Programming Language :: Python :: 3
Classifier: Programming Language :: Python :: 3.8
Classifier: Programming Language :: Python :: 3.9
Classifier: Programming Language :: Python :: 3.10
Classifier: Programming Language :: Python :: 3.11
Requires-Dist: typer[all] (>=0.7.0,<0.8.0)
